{
  "experiment": {
    "static_only": true,
    "seeds": 3,
    "seed_indices": [
      0,
      1,
      2
    ],
    "alns_max_iter": 100,
    "reference": "B3_Graph_ALNS"
  },
  "variants": {
    "B1_Plain_ALNS": {
      "label": "B1 Plain ALNS",
      "metrics": {
        "makespan_s": {
          "mean": 6740.115678273505,
          "std": 61.2482556637294,
          "ci95": [
            6687.507699999999,
            6807.3543628205125
          ],
          "n": 3
        },
        "distance_m": {
          "mean": 63873.33890999999,
          "std": 2123.1384656107975,
          "ci95": [
            61513.22978999999,
            65627.96343999999
          ],
          "n": 3
        },
        "energy_kwh": {
          "mean": 200.6182725478221,
          "std": 6.948914089815646,
          "ci95": [
            192.69034944327208,
            205.6538839794397
          ],
          "n": 3
        },
        "load_std_s": {
          "mean": 3544.9838714635594,
          "std": 247.2213615261599,
          "ci95": [
            3313.773340166765,
            3805.5879966176053
          ],
          "n": 3
        },
        "runtime_s": {
          "mean": 68.8501337046667,
          "std": 10.231303573863004,
          "ci95": [
            57.70388517399988,
            77.81448644800003
          ],
          "n": 3
        }
      },
      "paired_vs_B3": {
        "makespan_s": {
          "B3_improvement_mean": -101.96229216722259,
          "B3_improvement_pct": -1.5127676887786063,
          "sign_test_p": 0.25
        },
        "distance_m": {
          "B3_improvement_mean": -3594.5861299999983,
          "B3_improvement_pct": -5.627678451356535,
          "sign_test_p": 0.25
        },
        "energy_kwh": {
          "B3_improvement_mean": -11.70442600096255,
          "B3_improvement_pct": -5.834177441724568,
          "sign_test_p": 0.25
        },
        "load_std_s": {
          "B3_improvement_mean": 96.2249641220128,
          "B3_improvement_pct": 2.7143977973103155,
          "sign_test_p": 1.0
        },
        "runtime_s": {
          "B3_improvement_mean": 23.40840763966632,
          "B3_improvement_pct": 33.999073611210264,
          "sign_test_p": 0.25
        }
      }
    },
    "B2_Graph_Greedy": {
      "label": "B2 Graph + Greedy",
      "metrics": {
        "makespan_s": {
          "mean": 8621.96596949891,
          "std": 370.1748196461864,
          "ci95": [
            8248.772369444443,
            8989.046286111112
          ],
          "n": 3
        },
        "distance_m": {
          "mean": 103612.16603000001,
          "std": 7455.812092062332,
          "ci95": [
            97405.33743999997,
            111882.35815
          ],
          "n": 3
        },
        "energy_kwh": {
          "mean": 291.86839718300774,
          "std": 17.1811729835683,
          "ci95": [
            276.74439811816757,
            310.54980291838365
          ],
          "n": 3
        },
        "load_std_s": {
          "mean": 3325.411766911886,
          "std": 177.3111551086254,
          "ci95": [
            3120.6720029506464,
            3428.4654001462527
          ],
          "n": 3
        },
        "runtime_s": {
          "mean": 0.0009639249998751135,
          "std": 2.9584474348947935e-05,
          "ci95": [
            0.0009442010004931944,
            0.0009979419992305338
          ],
          "n": 3
        }
      },
      "paired_vs_B3": {
        "makespan_s": {
          "B3_improvement_mean": 1779.8879990581834,
          "B3_improvement_pct": 20.64364444669255,
          "sign_test_p": 0.25
        },
        "distance_m": {
          "B3_improvement_mean": 36144.24099,
          "B3_improvement_pct": 34.88416696117977,
          "sign_test_p": 0.25
        },
        "energy_kwh": {
          "B3_improvement_mean": 79.54569863422311,
          "B3_improvement_pct": 27.25396082685384,
          "sign_test_p": 0.25
        },
        "load_std_s": {
          "B3_improvement_mean": -123.34714042966107,
          "B3_improvement_pct": -3.7092290842588285,
          "sign_test_p": 1.0
        },
        "runtime_s": {
          "B3_improvement_mean": -45.440762140000516,
          "B3_improvement_pct": -4714138.7707433505,
          "sign_test_p": 0.25
        }
      }
    },
    "B3_Graph_ALNS": {
      "label": "B3 Graph + ALNS (full)",
      "metrics": {
        "makespan_s": {
          "mean": 6842.077970440726,
          "std": 44.79629959096667,
          "ci95": [
            6807.515373611111,
            6892.6876146341465
          ],
          "n": 3
        },
        "distance_m": {
          "mean": 67467.92503999999,
          "std": 2397.156511332435,
          "ci95": [
            64717.97723,
            69116.21125999998
          ],
          "n": 3
        },
        "energy_kwh": {
          "mean": 212.32269854878464,
          "std": 7.206894352134031,
          "ci95": [
            204.36965972805078,
            218.4208226206628
          ],
          "n": 3
        },
        "load_std_s": {
          "mean": 3448.758907341547,
          "std": 96.57832856552344,
          "ci95": [
            3379.349049743161,
            3559.0553521967036
          ],
          "n": 3
        },
        "runtime_s": {
          "mean": 45.44172606500039,
          "std": 4.772765887274579,
          "ci95": [
            40.90827984000043,
            50.42233812300037
          ],
          "n": 3
        }
      },
      "paired_vs_B3": {}
    },
    "B4_no_adaptive": {
      "label": "B4 w/o adaptive weights",
      "metrics": {
        "makespan_s": {
          "mean": 6857.909594951309,
          "std": 32.26139372970226,
          "ci95": [
            6828.959247142856,
            6892.6876146341465
          ],
          "n": 3
        },
        "distance_m": {
          "mean": 67998.17528333333,
          "std": 609.7400861035547,
          "ci95": [
            67356.23965999999,
            68569.58663
          ],
          "n": 3
        },
        "energy_kwh": {
          "mean": 212.49128694457343,
          "std": 1.4782297639359834,
          "ci95": [
            211.41923338335707,
            214.1776132976403
          ],
          "n": 3
        },
        "load_std_s": {
          "mean": 3608.412989387047,
          "std": 188.46199095374877,
          "ci95": [
            3407.8723200847767,
            3781.8646194701364
          ],
          "n": 3
        },
        "runtime_s": {
          "mean": 49.9347115106666,
          "std": 2.05825415610042,
          "ci95": [
            47.86306631499974,
            51.979308021999714
          ],
          "n": 3
        }
      },
      "paired_vs_B3": {
        "makespan_s": {
          "B3_improvement_mean": 15.831624510581605,
          "B3_improvement_pct": 0.23085204450984032,
          "sign_test_p": 0.5
        },
        "distance_m": {
          "B3_improvement_mean": 530.2502433333357,
          "B3_improvement_pct": 0.7798006948332075,
          "sign_test_p": 1.0
        },
        "energy_kwh": {
          "B3_improvement_mean": 0.1685883957887976,
          "B3_improvement_pct": 0.07933896877041009,
          "sign_test_p": 1.0
        },
        "load_std_s": {
          "B3_improvement_mean": 159.65408204550022,
          "B3_improvement_pct": 4.424495824482117,
          "sign_test_p": 0.5
        },
        "runtime_s": {
          "B3_improvement_mean": 4.4929854456662115,
          "B3_improvement_pct": 8.997719842051076,
          "sign_test_p": 1.0
        }
      }
    },
    "B5_no_SA": {
      "label": "B5 w/o simulated annealing",
      "metrics": {
        "makespan_s": {
          "mean": 6798.267711330317,
          "std": 118.74079691828204,
          "ci95": [
            6721.08987179487,
            6934.999703529411
          ],
          "n": 3
        },
        "distance_m": {
          "mean": 66223.4059,
          "std": 4863.626388172682,
          "ci95": [
            62874.82115999999,
            71802.19527
          ],
          "n": 3
        },
        "energy_kwh": {
          "mean": 209.86048243744676,
          "std": 14.302161216456984,
          "ci95": [
            199.00417271110618,
            226.06626318973792
          ],
          "n": 3
        },
        "load_std_s": {
          "mean": 3361.281816357969,
          "std": 40.75784012806873,
          "ci95": [
            3314.5276812843185,
            3389.321466016465
          ],
          "n": 3
        },
        "runtime_s": {
          "mean": 46.60899212166623,
          "std": 7.904284865386572,
          "ci95": [
            37.51336376499967,
            51.812456992999614
          ],
          "n": 3
        }
      },
      "paired_vs_B3": {
        "makespan_s": {
          "B3_improvement_mean": -43.81025911041039,
          "B3_improvement_pct": -0.6444326844821678,
          "sign_test_p": 1.0
        },
        "distance_m": {
          "B3_improvement_mean": -1244.5191399999967,
          "B3_improvement_pct": -1.8792738354159413,
          "sign_test_p": 1.0
        },
        "energy_kwh": {
          "B3_improvement_mean": -2.4622161113378715,
          "B3_improvement_pct": -1.1732633427409498,
          "sign_test_p": 1.0
        },
        "load_std_s": {
          "B3_improvement_mean": -87.47709098357745,
          "B3_improvement_pct": -2.6024920183086886,
          "sign_test_p": 1.0
        },
        "runtime_s": {
          "B3_improvement_mean": 1.1672660566658426,
          "B3_improvement_pct": 2.504379527493018,
          "sign_test_p": 1.0
        }
      }
    },
    "B6_no_bottleneck": {
      "label": "B6 w/o bottleneck destroy",
      "metrics": {
        "makespan_s": {
          "mean": 6814.342826862434,
          "std": 109.91760668207907,
          "ci95": [
            6736.496257142858,
            6940.080937333333
          ],
          "n": 3
        },
        "distance_m": {
          "mean": 65612.25396333332,
          "std": 1464.2414540058724,
          "ci95": [
            64065.44186,
            66976.87255999999
          ],
          "n": 3
        },
        "energy_kwh": {
          "mean": 204.28094440747543,
          "std": 1.9508670433071973,
          "ci95": [
            202.42037292123294,
            206.31104264784256
          ],
          "n": 3
        },
        "load_std_s": {
          "mean": 3558.9922607160606,
          "std": 89.97503678674883,
          "ci95": [
            3486.9175140803086,
            3659.8326464471024
          ],
          "n": 3
        },
        "runtime_s": {
          "mean": 59.6049134403332,
          "std": 7.864333863928779,
          "ci95": [
            51.357628621,
            67.02013099800024
          ],
          "n": 3
        }
      },
      "paired_vs_B3": {
        "makespan_s": {
          "B3_improvement_mean": -27.73514357829269,
          "B3_improvement_pct": -0.40701127435149803,
          "sign_test_p": 1.0
        },
        "distance_m": {
          "B3_improvement_mean": -1855.6710766666656,
          "B3_improvement_pct": -2.828238575226644,
          "sign_test_p": 1.0
        },
        "energy_kwh": {
          "B3_improvement_mean": -8.041754141309212,
          "B3_improvement_pct": -3.9366149224709246,
          "sign_test_p": 0.25
        },
        "load_std_s": {
          "B3_improvement_mean": 110.23335337451378,
          "B3_improvement_pct": 3.097319277461286,
          "sign_test_p": 0.25
        },
        "runtime_s": {
          "B3_improvement_mean": 14.163187375332805,
          "B3_improvement_pct": 23.76177827942104,
          "sign_test_p": 0.25
        }
      }
    },
    "B7_basic_operators": {
      "label": "B7 basic operators only",
      "metrics": {
        "makespan_s": {
          "mean": 6891.79047638889,
          "std": 39.60516083454395,
          "ci95": [
            6854.544970833333,
            6933.394700000001
          ],
          "n": 3
        },
        "distance_m": {
          "mean": 70385.48747666668,
          "std": 1413.848536028497,
          "ci95": [
            68752.93457000001,
            71208.54169
          ],
          "n": 3
        },
        "energy_kwh": {
          "mean": 217.97809382928745,
          "std": 4.361342622767369,
          "ci95": [
            213.04955158678536,
            221.3386980337569
          ],
          "n": 3
        },
        "load_std_s": {
          "mean": 3588.347920623795,
          "std": 135.54768840645474,
          "ci95": [
            3435.2720052420887,
            3693.1524474356593
          ],
          "n": 3
        },
        "runtime_s": {
          "mean": 36.954607842000165,
          "std": 8.467910415511426,
          "ci95": [
            32.060225211000215,
            46.73250654500043
          ],
          "n": 3
        }
      },
      "paired_vs_B3": {
        "makespan_s": {
          "B3_improvement_mean": 49.71250594816229,
          "B3_improvement_pct": 0.7213293282562223,
          "sign_test_p": 1.0
        },
        "distance_m": {
          "B3_improvement_mean": 2917.562436666672,
          "B3_improvement_pct": 4.145119315446761,
          "sign_test_p": 1.0
        },
        "energy_kwh": {
          "B3_improvement_mean": 5.655395280502792,
          "B3_improvement_pct": 2.5944787300194916,
          "sign_test_p": 1.0
        },
        "load_std_s": {
          "B3_improvement_mean": 139.58901328224783,
          "B3_improvement_pct": 3.8900635158583454,
          "sign_test_p": 0.25
        },
        "runtime_s": {
          "B3_improvement_mean": -8.487118223000229,
          "B3_improvement_pct": -22.9663328028997,
          "sign_test_p": 0.25
        }
      }
    }
  }
}